py_fort_hermes/FrameReadout_pb2.py
py_fort_hermes/Header_pb2.py
py_fort_hermes/Tag_pb2.py
py_fort_hermes/__init__.py
py_fort_hermes/check.py
py_fort_hermes/errors.py
py_fort_hermes/file.py
py_fort_hermes/network.py
py_fort_hermes/utils.py
py_fort_hermes/protobuf/FrameReadout.proto
py_fort_hermes/protobuf/Header.proto
py_fort_hermes/protobuf/Tag.proto
formicidae_tracker_hermes-0.5.2.dist-info/METADATA
formicidae_tracker_hermes-0.5.2.dist-info/WHEEL
formicidae_tracker_hermes-0.5.2.dist-info/top_level.txt
formicidae_tracker_hermes-0.5.2.dist-info/RECORD
