Metadata-Version: 2.1
Name: formicidae-tracker-hermes
Version: 0.5.2
Summary: FORmicidae Tracker hermes python implementation
Home-page: https://github.com/formicidae-tracker/hermes
Author: Alexandre Tuleu
Author-email: alexandre.tuleu.2005@polytechnique.org
License: UNKNOWN
Project-URL: Bug Tracker, https://github.com/formicidae-tracker/hermes/issues
Platform: UNKNOWN
Classifier: Programming Language :: Python :: 3
Classifier: License :: OSI Approved :: GNU Lesser General Public License v3 (LGPLv3)
Classifier: Operating System :: OS Independent
Requires-Python: >=3.6
Requires-Dist: protobuf
